LICENSE.txt
README.md
setup.py
segna/__init__.py
segna/base.py
segna/constants.py
segna/job_config.py
segna/job_run.py
segna/platform_utils.py
segna/platform_utils_constants.py
segna/utils.py
segna.egg-info/PKG-INFO
segna.egg-info/SOURCES.txt
segna.egg-info/dependency_links.txt
segna.egg-info/requires.txt
segna.egg-info/top_level.txt