Metadata-Version: 2.1
Name: segna
Version: 1.1.0
Summary: Run Segna pipelines from your Python code!
Home-page: https://segna.io
Author: Segna
Author-email: josh@segna.io
License: MIT
Keywords: Segna,API
Platform: UNKNOWN
Classifier: License :: OSI Approved :: MIT License
Classifier: Intended Audience :: Developers
Classifier: Programming Language :: Python :: 3
License-File: LICENSE.txt
